Workbook

Sheet Welcome
B1: Welcome to my Monte Carlo Simulation model.
B5: In this spreadsheet you will find 4 sheets. | K5: Why did the spreadsheet break up with the calculator?
B6: Assumptions sheet: Includes various assumptions made for the model. | K6: Because it found someone with more functions.
B7: Monte Carlo Sim sheet: Includes the actual simulation.
B8: Histogram sheet: Includes various diagrams from the data.
B9: Reflection sheet: Includes my technical and personal reflections for the project.
B20: Aadit Singh

Sheet Assumptions
C1: Assumptions
C3: Variable | D3: Low Amount | F3: High Amount | G3: Length | H3: Source
C4: Food $ Grocerries | D4: 25000 | E4: to | F4: 30000 | G4: Annual | H4: https://www.wits.ac.za/internationalstudents/financial-information/average-living-costs/
C5: Transport | D5: =3000*12 -> 36000 | E5: to | F5: =4000*12 -> 48000 | G5: Annual | H5: https://www.cars.co.za/motoring-news/understanding-total-cost-of-ownership-for-cars-in-south-africa/299920/?
C6: Car | D6: =500000 -> 500000 | E6: to | F6: =2000000 -> 2000000 | G6: Lifetime | H6: https://www.cars.co.za/motoring-news/understanding-total-cost-of-ownership-for-cars-in-south-africa/299920/?
C7: Housing | D7: =1500000 -> 1500000 | E7: to | F7: 4000000 | G7: Lifetime | H7: https://theafricanvestor.com/blogs/news/average-house-price-south-africa?
C8: Utilities | D8: =1500*12 -> 18000 | E8: to | F8: =3000*12 -> 36000 | G8: Annual | H8: https://copound.com/cost-of-living-south-africa-c201
C9: Schooling fees | D9: =100000 -> 100000 | E9: to | F9: =300000 -> 300000 | G9: Annual | H9: https://modernclassroom.co.za/how-much-are-school-fees-in-south-africa-a-parents-guide/?
C10: Childcare | D10: =2000*12 -> 24000 | E10: to | F10: =5000*12 -> 60000 | G10: Annual | H10: https://www.numbeo.com/cost-of-living/region_prices_by_city?itemId=224&region=018&
C11: Health Insurance | D11: =3000 *12 -> 36000 | E11: to | F11: =10000*12 -> 120000 | G11: Annual | H11: https://travelpander.com/how-much-is-medical-aid-in-south-africa/?
C12: Overall household spending | D12: =140000 -> 140000 | E12: to | F12: =250000 -> 250000 | G12: Annual | H12: https://www.statssa.gov.za/?p=17981&
C13: Leisure/Travel | D13: =150000 -> 150000 | E13: to | F13: =500000 -> 500000 | G13: Annual | H13: https://www.southafrica.net/gl/en/trade/press/south-africa-the-adventure-capital-of-the-world
C14: Technology/Subscriptions | D14: =8000*12 -> 96000 | E14: to | F14: =15000*12 -> 180000 | G14: Annual | H14: https://www.livingcost.net/south-africa?
C15: Income | D15: =480000 -> 480000 | E15: to | F15: =4000000 -> 4000000 | G15: Annual | H15: https://www.salaryexpert.com/salary/job/it-specialist/south-africa
C16: Tax | D16: 80000 | E16: to | F16: 400000 | G16: Annual | H16: https://codera.co.za/tax-paid-by-income-group-in-south-africa/#:~:text=The%20latest%20tax%20statistics%20for,the%20total%20personal%20tax%20liability.
C17: Rent | D17: =8000*12 -> 96000 | E17: to | F17: =12000*12 -> 144000 | G17: Annual | H17: https://businesstech.co.za/news/property/772049/the-average-rent-in-south-africas-provinces/
C18: Investment | D18: =100000*(1+12%)^44 -> 14641750
C21: Please Note:
C22: Annual expenses will be multiplied by the amount of years it will be used for in the simulation. E.g: Tax will be multiplied by 44 as the average age for a male to live to in South Africa is 65, since I am 21, 65-21=44.
C23: Lifetime expenses will be multiplied by a random number with in reason. E.g: Car will be multiplied by numbers between 3 and 5 to estimate the amount of cars I will own.

Sheet Monte Carlo Simulation
A1: Scenario | B1: Food and Grocerries | C1: Transport | D1: Car | E1: Rent | F1: Housing | G1: Utilities | H1: Schooling fees | I1: Childcare | J1: Health Insurance | K1: Overall Househol Spending | L1: Leisure/Travel | M1: Technology/Subscriptions | N1: Tax | O1: Income | P1: Investment | Q1: Money In Bank | R1: Total Money Left
A2: 1 | B2: =_xlfn.NORM.INV(RAND(),AVERAGE(Assumptions!$D$4,Assumptions!$F$4),(Assumptions!$F$4-Assumptions!$D$4)/3.29)*44 -> 1150938.8 | C2: =_xlfn.NORM.INV(RAND(),AVERAGE(Assumptions!$D$5,Assumptions!$F$5),(Assumptions!$F$5-Assumptions!$D$5)/3.29)*44 -> 1999197.4 | D2: =_xlfn.NORM.INV(RAND(),AVERAGE(Assumptions!$D$6,Assumptions!$F$6),(Assumptions!$F$6-Assumptions!$D$6)/3.29)*RANDBETWEEN(2,5) -> 1189999.7 | E2: =_xlfn.NORM.INV(RAND(),AVERAGE(Assumptions!$D$17,Assumptions!$F$17),(Assumptions!$F$17-Assumptions!$D$17)/3.29)*8 -> 952255.11 | F2: =_xlfn.NORM.INV(RAND(),AVERAGE(Assumptions!$D$7,Assumptions!$F$7),(Assumptions!$F$7-Assumptions!$D$7)/3.29)*RANDBETWEEN(1,3) -> 9667850.3 | G2: =_xlfn.NORM.INV(RAND(),AVERAGE(Assumptions!$D$8,Assumptions!$F$8),(Assumptions!$F$8-Assumptions!$D$8)/3.29)*44 -> 1123592.9 | H2: =_xlfn.NORM.INV(RAND(),AVERAGE(Assumptions!$D$9,Assumptions!$F$9),(Assumptions!$F$9-Assumptions!$D$9)/3.29)*21 -> 5178638.3 | I2: =_xlfn.NORM.INV(RAND(),AVERAGE(Assumptions!$D$10,Assumptions!$F$10),(Assumptions!$F$10-Assumptions!$D$10)/3.29)*21 -> 703921.86 | J2: =NORMINV(RAND(),AVERAGE(Assumptions!$D$11,Assumptions!$F$11),(Assumptions!$F$11-Assumptions!$D$11)/3.29)*44 -> 2535618 | K2: =_xlfn.NORM.INV(RAND(),AVERAGE(Assumptions!$D$12,Assumptions!$F$12),(Assumptions!$F$12-Assumptions!$D$12)/3.29)*44 -> 9200575 | L2: =_xlfn.NORM.INV(RAND(),AVERAGE(Assumptions!$D$13,Assumptions!$F$13),(Assumptions!$F$13-Assumptions!$D$13)/3.29)*44 -> 5520502.8 | M2: =_xlfn.NORM.INV(RAND(),AVERAGE(Assumptions!$D$14,Assumptions!$F$14),(Assumptions!$F$14-Assumptions!$D$14)/3.29)*44 -> 6808423.7 | N2: =_xlfn.NORM.INV(RAND(),AVERAGE(Assumptions!$D$16,Assumptions!$F$16),(Assumptions!$F$16-Assumptions!$D$16)/3.29)*44 -> 8107549.1 | O2: =_xlfn.NORM.INV(RAND(),AVERAGE(Assumptions!$D$15,Assumptions!$F$15),(Assumptions!$F$15-Assumptions!$D$15)/3.29)*44 -> 72278211 | P2: =Assumptions!$D$18 -> 14641750 | Q2: =O2-(B2+C2+D2+F2+G2+H2+I2+J2+K2+L2+M2+N2+E2) -> 18139148 | R2: =Q2+P2 -> 32780899
A3: 2 | B3: =_xlfn.NORM.INV(RAND(),AVERAGE(Assumptions!$D$4,Assumptions!$F$4),(Assumptions!$F$4-Assumptions!$D$4)/3.29)*44 -> 1224735.2 | C3: =_xlfn.NORM.INV(RAND(),AVERAGE(Assumptions!$D$5,Assumptions!$F$5),(Assumptions!$F$5-Assumptions!$D$5)/3.29)*44 -> 1890378.9 | D3: =_xlfn.NORM.INV(RAND(),AVERAGE(Assumptions!$D$6,Assumptions!$F$6),(Assumptions!$F$6-Assumptions!$D$6)/3.29)*RANDBETWEEN(2,5) -> 3173710.6 | E3: =_xlfn.NORM.INV(RAND(),AVERAGE(Assumptions!$D$17,Assumptions!$F$17),(Assumptions!$F$17-Assumptions!$D$17)/3.29)*8 -> 896491.61 | F3: =_xlfn.NORM.INV(RAND(),AVERAGE(Assumptions!$D$7,Assumptions!$F$7),(Assumptions!$F$7-Assumptions!$D$7)/3.29)*RANDBETWEEN(1,3) -> 2013998.6 | G3: =_xlfn.NORM.INV(RAND(),AVERAGE(Assumptions!$D$8,Assumptions!$F$8),(Assumptions!$F$8-Assumptions!$D$8)/3.29)*44 -> 1140928.7 | H3: =_xlfn.NORM.INV(RAND(),AVERAGE(Assumptions!$D$9,Assumptions!$F$9),(Assumptions!$F$9-Assumptions!$D$9)/3.29)*21 -> 3269329.6 | I3: =_xlfn.NORM.INV(RAND(),AVERAGE(Assumptions!$D$10,Assumptions!$F$10),(Assumptions!$F$10-Assumptions!$D$10)/3.29)*21 -> 852576.42 | J3: =NORMINV(RAND(),AVERAGE(Assumptions!$D$11,Assumptions!$F$11),(Assumptions!$F$11-Assumptions!$D$11)/3.29)*44 -> 4061889.6 | K3: =_xlfn.NORM.INV(RAND(),AVERAGE(Assumptions!$D$12,Assumptions!$F$12),(Assumptions!$F$12-Assumptions!$D$12)/3.29)*44 -> 7081723.7 | L3: =_xlfn.NORM.INV(RAND(),AVERAGE(Assumptions!$D$13,Assumptions!$F$13),(Assumptions!$F$13-Assumptions!$D$13)/3.29)*44 -> 17734918 | M3: =_xlfn.NORM.INV(RAND(),AVERAGE(Assumptions!$D$14,Assumptions!$F$14),(Assumptions!$F$14-Assumptions!$D$14)/3.29)*44 -> 5694430.1 | N3: =_xlfn.NORM.INV(RAND(),AVERAGE(Assumptions!$D$16,Assumptions!$F$16),(Assumptions!$F$16-Assumptions!$D$16)/3.29)*44 -> 3913664.4 | O3: =_xlfn.NORM.INV(RAND(),AVERAGE(Assumptions!$D$15,Assumptions!$F$15),(Assumptions!$F$15-Assumptions!$D$15)/3.29)*44 -> 1.2283173e+08 | P3: =Assumptions!$D$18 -> 14641750 | Q3: =O3-(B3+C3+D3+F3+G3+H3+I3+J3+K3+L3+M3+N3+E3) -> 69882957 | R3: =Q3+P3 -> 84524707
A4: 3 | B4: =_xlfn.NORM.INV(RAND(),AVERAGE(Assumptions!$D$4,Assumptions!$F$4),(Assumptions!$F$4-Assumptions!$D$4)/3.29)*44 -> 1162762.3 | C4: =_xlfn.NORM.INV(RAND(),AVERAGE(Assumptions!$D$5,Assumptions!$F$5),(Assumptions!$F$5-Assumptions!$D$5)/3.29)*44 -> 2117262.6 | D4: =_xlfn.NORM.INV(RAND(),AVERAGE(Assumptions!$D$6,Assumptions!$F$6),(Assumptions!$F$6-Assumptions!$D$6)/3.29)*RANDBETWEEN(2,5) -> 2421347.1 | E4: =_xlfn.NORM.INV(RAND(),AVERAGE(Assumptions!$D$17,Assumptions!$F$17),(Assumptions!$F$17-Assumptions!$D$17)/3.29)*8 -> 1073934.3 | F4: =_xlfn.NORM.INV(RAND(),AVERAGE(Assumptions!$D$7,Assumptions!$F$7),(Assumptions!$F$7-Assumptions!$D$7)/3.29)*RANDBETWEEN(1,3) -> 10901188 | G4: =_xlfn.NORM.INV(RAND(),AVERAGE(Assumptions!$D$8,Assumptions!$F$8),(Assumptions!$F$8-Assumptions!$D$8)/3.29)*44 -> 1270846.3 | H4: =_xlfn.NORM.INV(RAND(),AVERAGE(Assumptions!$D$9,Assumptions!$F$9),(Assumptions!$F$9-Assumptions!$D$9)/3.29)*21 -> 4024903.1 | I4: =_xlfn.NORM.INV(RAND(),AVERAGE(Assumptions!$D$10,Assumptions!$F$10),(Assumptions!$F$10-Assumptions!$D$10)/3.29)*21 -> 668601.68 | J4: =NORMINV(RAND(),AVERAGE(Assumptions!$D$11,Assumptions!$F$11),(Assumptions!$F$11-Assumptions!$D$11)/3.29)*44 -> 4177045.2 | K4: =_xlfn.NORM.INV(RAND(),AVERAGE(Assumptions!$D$12,Assumptions!$F$12),(Assumptions!$F$12-Assumptions!$D$12)/3.29)*44 -> 9012140.7 | L4: =_xlfn.NORM.INV(RAND(),AVERAGE(Assumptions!$D$13,Assumptions!$F$13),(Assumptions!$F$13-Assumptions!$D$13)/3.29)*44 -> 12130939 | M4: =_xlfn.NORM.INV(RAND(),AVERAGE(Assumptions!$D$14,Assumptions!$F$14),(Assumptions!$F$14-Assumptions!$D$14)/3.29)*44 -> 5840449.4 | N4: =_xlfn.NORM.INV(RAND(),AVERAGE(Assumptions!$D$16,Assumptions!$F$16),(Assumptions!$F$16-Assumptions!$D$16)/3.29)*44 -> 8057066.4 | O4: =_xlfn.NORM.INV(RAND(),AVERAGE(Assumptions!$D$15,Assumptions!$F$15),(Assumptions!$F$15-Assumptions!$D$15)/3.29)*44 -> 1.6355964e+08 | P4: =Assumptions!$D$18 -> 14641750 | Q4: =O4-(B4+C4+D4+F4+G4+H4+I4+J4+K4+L4+M4+N4+E4) -> 1.0070116e+08 | R4: =Q4+P4 -> 1.1534291e+08
A5: 4 | B5: =_xlfn.NORM.INV(RAND(),AVERAGE(Assumptions!$D$4,Assumptions!$F$4),(Assumptions!$F$4-Assumptions!$D$4)/3.29)*44 -> 1153364.3 | C5: =_xlfn.NORM.INV(RAND(),AVERAGE(Assumptions!$D$5,Assumptions!$F$5),(Assumptions!$F$5-Assumptions!$D$5)/3.29)*44 -> 1859518.6 | D5: =_xlfn.NORM.INV(RAND(),AVERAGE(Assumptions!$D$6,Assumptions!$F$6),(Assumptions!$F$6-Assumptions!$D$6)/3.29)*RANDBETWEEN(2,5) -> 5836942.4 | E5: =_xlfn.NORM.INV(RAND(),AVERAGE(Assumptions!$D$17,Assumptions!$F$17),(Assumptions!$F$17-Assumptions!$D$17)/3.29)*8 -> 834346.52 | F5: =_xlfn.NORM.INV(RAND(),AVERAGE(Assumptions!$D$7,Assumptions!$F$7),(Assumptions!$F$7-Assumptions!$D$7)/3.29)*RANDBETWEEN(1,3) -> 3682287.4 | G5: =_xlfn.NORM.INV(RAND(),AVERAGE(Assumptions!$D$8,Assumptions!$F$8),(Assumptions!$F$8-Assumptions!$D$8)/3.29)*44 -> 1505777 | H5: =_xlfn.NORM.INV(RAND(),AVERAGE(Assumptions!$D$9,Assumptions!$F$9),(Assumptions!$F$9-Assumptions!$D$9)/3.29)*21 -> 3560994.4 | I5: =_xlfn.NORM.INV(RAND(),AVERAGE(Assumptions!$D$10,Assumptions!$F$10),(Assumptions!$F$10-Assumptions!$D$10)/3.29)*21 -> 774777.83 | J5: =NORMINV(RAND(),AVERAGE(Assumptions!$D$11,Assumptions!$F$11),(Assumptions!$F$11-Assumptions!$D$11)/3.29)*44 -> 2925979.2 | K5: =_xlfn.NORM.INV(RAND(),AVERAGE(Assumptions!$D$12,Assumptions!$F$12),(Assumptions!$F$12-Assumptions!$D$12)/3.29)*44 -> 6882367.7 | L5: =_xlfn.NORM.INV(RAND(),AVERAGE(Assumptions!$D$13,Assumptions!$F$13),(Assumptions!$F$13-Assumptions!$D$13)/3.29)*44 -> 7804790.5 | M5: =_xlfn.NORM.INV(RAND(),AVERAGE(Assumptions!$D$14,Assumptions!$F$14),(Assumptions!$F$14-Assumptions!$D$14)/3.29)*44 -> 7518893.1 | N5: =_xlfn.NORM.INV(RAND(),AVERAGE(Assumptions!$D$16,Assumptions!$F$16),(Assumptions!$F$16-Assumptions!$D$16)/3.29)*44 -> 9966667.5 | O5: =_xlfn.NORM.INV(RAND(),AVERAGE(Assumptions!$D$15,Assumptions!$F$15),(Assumptions!$F$15-Assumptions!$D$15)/3.29)*44 -> 66211910 | P5: =Assumptions!$D$18 -> 14641750 | Q5: =O5-(B5+C5+D5+F5+G5+H5+I5+J5+K5+L5+M5+N5+E5) -> 11905203 | R5: =Q5+P5 -> 26546954
A6: 5 | B6: =_xlfn.NORM.INV(RAND(),AVERAGE(Assumptions!$D$4,Assumptions!$F$4),(Assumptions!$F$4-Assumptions!$D$4)/3.29)*44 -> 1083075.4 | C6: =_xlfn.NORM.INV(RAND(),AVERAGE(Assumptions!$D$5,Assumptions!$F$5),(Assumptions!$F$5-Assumptions!$D$5)/3.29)*44 -> 2100656.7 | D6: =_xlfn.NORM.INV(RAND(),AVERAGE(Assumptions!$D$6,Assumptions!$F$6),(Assumptions!$F$6-Assumptions!$D$6)/3.29)*RANDBETWEEN(2,5) -> 2331825.3 | E6: =_xlfn.NORM.INV(RAND(),AVERAGE(Assumptions!$D$17,Assumptions!$F$17),(Assumptions!$F$17-Assumptions!$D$17)/3.29)*8 -> 910360.44 | F6: =_xlfn.NORM.INV(RAND(),AVERAGE(Assumptions!$D$7,Assumptions!$F$7),(Assumptions!$F$7-Assumptions!$D$7)/3.29)*RANDBETWEEN(1,3) -> 3874774.6 | G6: =_xlfn.NORM.INV(RAND(),AVERAGE(Assumptions!$D$8,Assumptions!$F$8),(Assumptions!$F$8-Assumptions!$D$8)/3.29)*44 -> 712929.77 | H6: =_xlfn.NORM.INV(RAND(),AVERAGE(Assumptions!$D$9,Assumptions!$F$9),(Assumptions!$F$9-Assumptions!$D$9)/3.29)*21 -> 1461663.3 | I6: =_xlfn.NORM.INV(RAND(),AVERAGE(Assumptions!$D$10,Assumptions!$F$10),(Assumptions!$F$10-Assumptions!$D$10)/3.29)*21 -> 1032450.7 | J6: =NORMINV(RAND(),AVERAGE(Assumptions!$D$11,Assumptions!$F$11),(Assumptions!$F$11-Assumptions!$D$11)/3.29)*44 -> 2291260.6 | K6: =_xlfn.NORM.INV(RAND(),AVERAGE(Assumptions!$D$12,Assumptions!$F$12),(Assumptions!$F$12-Assumptions!$D$12)/3.29)*44 -> 6440923.7 | L6: =_xlfn.NORM.INV(RAND(),AVERAGE(Assumptions!$D$13,Assumptions!$F$13),(Assumptions!$F$13-Assumptions!$D$13)/3.29)*44 -> 5946602.7 | M6: =_xlfn.NORM.INV(RAND(),AVERAGE(Assumptions!$D$14,Assumptions!$F$14),(Assumptions!$F$14-Assumptions!$D$14)/3.29)*44 -> 7956611 | N6: =_xlfn.NORM.INV(RAND(),AVERAGE(Assumptions!$D$16,Assumptions!$F$16),(Assumptions!$F$16-Assumptions!$D$16)/3.29)*44 -> 2889842.9 | O6: =_xlfn.NORM.INV(RAND(),AVERAGE(Assumptions!$D$15,Assumptions!$F$15),(Assumptions!$F$15-Assumptions!$D$15)/3.29)*44 -> 93514599 | P6: =Assumptions!$D$18 -> 14641750 | Q6: =O6-(B6+C6+D6+F6+G6+H6+I6+J6+K6+L6+M6+N6+E6) -> 54481622 | R6: =Q6+P6 -> 69123372
A7: 6 | B7: =_xlfn.NORM.INV(RAND(),AVERAGE(Assumptions!$D$4,Assumptions!$F$4),(Assumptions!$F$4-Assumptions!$D$4)/3.29)*44 -> 1116716.8 | C7: =_xlfn.NORM.INV(RAND(),AVERAGE(Assumptions!$D$5,Assumptions!$F$5),(Assumptions!$F$5-Assumptions!$D$5)/3.29)*44 -> 1790832.8 | D7: =_xlfn.NORM.INV(RAND(),AVERAGE(Assumptions!$D$6,Assumptions!$F$6),(Assumptions!$F$6-Assumptions!$D$6)/3.29)*RANDBETWEEN(2,5) -> 2588180.5 | E7: =_xlfn.NORM.INV(RAND(),AVERAGE(Assumptions!$D$17,Assumptions!$F$17),(Assumptions!$F$17-Assumptions!$D$17)/3.29)*8 -> 1064388.5 | F7: =_xlfn.NORM.INV(RAND(),AVERAGE(Assumptions!$D$7,Assumptions!$F$7),(Assumptions!$F$7-Assumptions!$D$7)/3.29)*RANDBETWEEN(1,3) -> 7754702.6 | G7: =_xlfn.NORM.INV(RAND(),AVERAGE(Assumptions!$D$8,Assumptions!$F$8),(Assumptions!$F$8-Assumptions!$D$8)/3.29)*44 -> 1537527.1 | H7: =_xlfn.NORM.INV(RAND(),AVERAGE(Assumptions!$D$9,Assumptions!$F$9),(Assumptions!$F$9-Assumptions!$D$9)/3.29)*21 -> 3285908.3 | I7: =_xlfn.NORM.INV(RAND(),AVERAGE(Assumptions!$D$10,Assumptions!$F$10),(Assumptions!$F$10-Assumptions!$D$10)/3.29)*21 -> 1351216.5 | J7: =NORMINV(RAND(),AVERAGE(Assumptions!$D$11,Assumptions!$F$11),(Assumptions!$F$11-Assumptions!$D$11)/3.29)*44 -> 3440213.8 | K7: =_xlfn.NORM.INV(RAND(),AVERAGE(Assumptions!$D$12,Assumptions!$F$12),(Assumptions!$F$12-Assumptions!$D$12)/3.29)*44 -> 6621223.5 | L7: =_xlfn.NORM.INV(RAND(),AVERAGE(Assumptions!$D$13,Assumptions!$F$13),(Assumptions!$F$13-Assumptions!$D$13)/3.29)*44 -> 13088412 | M7: =_xlfn.NORM.INV(RAND(),AVERAGE(Assumptions!$D$14,Assumptions!$F$14),(Assumptions!$F$14-Assumptions!$D$14)/3.29)*44 -> 6518105.9 | N7: =_xlfn.NORM.INV(RAND(),AVERAGE(Assumptions!$D$16,Assumptions!$F$16),(Assumptions!$F$16-Assumptions!$D$16)/3.29)*44 -> 15765032 | O7: =_xlfn.NORM.INV(RAND(),AVERAGE(Assumptions!$D$15,Assumptions!$F$15),(Assumptions!$F$15-Assumptions!$D$15)/3.29)*44 -> 1.046416e+08 | P7: =Assumptions!$D$18 -> 14641750 | Q7: =O7-(B7+C7+D7+F7+G7+H7+I7+J7+K7+L7+M7+N7+E7) -> 38719135 | R7: =Q7+P7 -> 53360886
A8: 7 | B8: =_xlfn.NORM.INV(RAND(),AVERAGE(Assumptions!$D$4,Assumptions!$F$4),(Assumptions!$F$4-Assumptions!$D$4)/3.29)*44 -> 1206663.5 | C8: =_xlfn.NORM.INV(RAND(),AVERAGE(Assumptions!$D$5,Assumptions!$F$5),(Assumptions!$F$5-Assumptions!$D$5)/3.29)*44 -> 2153159.2 | D8: =_xlfn.NORM.INV(RAND(),AVERAGE(Assumptions!$D$6,Assumptions!$F$6),(Assumptions!$F$6-Assumptions!$D$6)/3.29)*RANDBETWEEN(2,5) -> 5112719.3 | E8: =_xlfn.NORM.INV(RAND(),AVERAGE(Assumptions!$D$17,Assumptions!$F$17),(Assumptions!$F$17-Assumptions!$D$17)/3.29)*8 -> 1153672 | F8: =_xlfn.NORM.INV(RAND(),AVERAGE(Assumptions!$D$7,Assumptions!$F$7),(Assumptions!$F$7-Assumptions!$D$7)/3.29)*RANDBETWEEN(1,3) -> 8052434.3 | G8: =_xlfn.NORM.INV(RAND(),AVERAGE(Assumptions!$D$8,Assumptions!$F$8),(Assumptions!$F$8-Assumptions!$D$8)/3.29)*44 -> 712310.94 | H8: =_xlfn.NORM.INV(RAND(),AVERAGE(Assumptions!$D$9,Assumptions!$F$9),(Assumptions!$F$9-Assumptions!$D$9)/3.29)*21 -> 4668603.1 | I8: =_xlfn.NORM.INV(RAND(),AVERAGE(Assumptions!$D$10,Assumptions!$F$10),(Assumptions!$F$10-Assumptions!$D$10)/3.29)*21 -> 710720.6 | J8: =NORMINV(RAND(),AVERAGE(Assumptions!$D$11,Assumptions!$F$11),(Assumptions!$F$11-Assumptions!$D$11)/3.29)*44 -> 2895224 | K8: =_xlfn.NORM.INV(RAND(),AVERAGE(Assumptions!$D$12,Assumptions!$F$12),(Assumptions!$F$12-Assumptions!$D$12)/3.29)*44 -> 10365497 | L8: =_xlfn.NORM.INV(RAND(),AVERAGE(Assumptions!$D$13,Assumptions!$F$13),(Assumptions!$F$13-Assumptions!$D$13)/3.29)*44 -> 13690446 | M8: =_xlfn.NORM.INV(RAND(),AVERAGE(Assumptions!$D$14,Assumptions!$F$14),(Assumptions!$F$14-Assumptions!$D$14)/3.29)*44 -> 5485361.5 | N8: =_xlfn.NORM.INV(RAND(),AVERAGE(Assumptions!$D$16,Assumptions!$F$16),(Assumptions!$F$16-Assumptions!$D$16)/3.29)*44 -> 3380814.6 | O8: =_xlfn.NORM.INV(RAND(),AVERAGE(Assumptions!$D$15,Assumptions!$F$15),(Assumptions!$F$15-Assumptions!$D$15)/3.29)*44 -> -10043334 | P8: =Assumptions!$D$18 -> 14641750 | Q8: =O8-(B8+C8+D8+F8+G8+H8+I8+J8+K8+L8+M8+N8+E8) -> -69630959 | R8: =Q8+P8 -> -54989209
A9: 8 | B9: =_xlfn.NORM.INV(RAND(),AVERAGE(Assumptions!$D$4,Assumptions!$F$4),(Assumptions!$F$4-Assumptions!$D$4)/3.29)*44 -> 1163879.8 | C9: =_xlfn.NORM.INV(RAND(),AVERAGE(Assumptions!$D$5,Assumptions!$F$5),(Assumptions!$F$5-Assumptions!$D$5)/3.29)*44 -> 2031193.6 | D9: =_xlfn.NORM.INV(RAND(),AVERAGE(Assumptions!$D$6,Assumptions!$F$6),(Assumptions!$F$6-Assumptions!$D$6)/3.29)*RANDBETWEEN(2,5) -> 3801668.7 | E9: =_xlfn.NORM.INV(RAND(),AVERAGE(Assumptions!$D$17,Assumptions!$F$17),(Assumptions!$F$17-Assumptions!$D$17)/3.29)*8 -> 944690.28 | F9: =_xlfn.NORM.INV(RAND(),AVERAGE(Assumptions!$D$7,Assumptions!$F$7),(Assumptions!$F$7-Assumptions!$D$7)/3.29)*RANDBETWEEN(1,3) -> 9448724.8 | G9: =_xlfn.NORM.INV(RAND(),AVERAGE(Assumptions!$D$8,Assumptions!$F$8),(Assumptions!$F$8-Assumptions!$D$8)/3.29)*44 -> 1361000 | H9: =_xlfn.NORM.INV(RAND(),AVERAGE(Assumptions!$D$9,Assumptions!$F$9),(Assumptions!$F$9-Assumptions!$D$9)/3.29)*21 -> 3953845.9 | I9: =_xlfn.NORM.INV(RAND(),AVERAGE(Assumptions!$D$10,Assumptions!$F$10),(Assumptions!$F$10-Assumptions!$D$10)/3.29)*21 -> 441867.56 | J9: =NORMINV(RAND(),AVERAGE(Assumptions!$D$11,Assumptions!$F$11),(Assumptions!$F$11-Assumptions!$D$11)/3.29)*44 -> 3843767.1 | K9: =_xlfn.NORM.INV(RAND(),AVERAGE(Assumptions!$D$12,Assumptions!$F$12),(Assumptions!$F$12-Assumptions!$D$12)/3.29)*44 -> 10836856 | L9: =_xlfn.NORM.INV(RAND(),AVERAGE(Assumptions!$D$13,Assumptions!$F$13),(Assumptions!$F$13-Assumptions!$D$13)/3.29)*44 -> 8915162.8 | M9: =_xlfn.NORM.INV(RAND(),AVERAGE(Assumptions!$D$14,Assumptions!$F$14),(Assumptions!$F$14-Assumptions!$D$14)/3.29)*44 -> 7330680.1 | N9: =_xlfn.NORM.INV(RAND(),AVERAGE(Assumptions!$D$16,Assumptions!$F$16),(Assumptions!$F$16-Assumptions!$D$16)/3.29)*44 -> 14123400 | O9: =_xlfn.NORM.INV(RAND(),AVERAGE(Assumptions!$D$15,Assumptions!$F$15),(Assumptions!$F$15-Assumptions!$D$15)/3.29)*44 -> 78263478 | P9: =Assumptions!$D$18 -> 14641750 | Q9: =O9-(B9+C9+D9+F9+G9+H9+I9+J9+K9+L9+M9+N9+E9) -> 10066741 | R9: =Q9+P9 -> 24708492
A10: 9 | B10: =_xlfn.NORM.INV(RAND(),AVERAGE(Assumptions!$D$4,Assumptions!$F$4),(Assumptions!$F$4-Assumptions!$D$4)/3.29)*44 -> 1257540.7 | C10: =_xlfn.NORM.INV(RAND(),AVERAGE(Assumptions!$D$5,Assumptions!$F$5),(Assumptions!$F$5-Assumptions!$D$5)/3.29)*44 -> 1817290 | D10: =_xlfn.NORM.INV(RAND(),AVERAGE(Assumptions!$D$6,Assumptions!$F$6),(Assumptions!$F$6-Assumptions!$D$6)/3.29)*RANDBETWEEN(2,5) -> 1817586.9 | E10: =_xlfn.NORM.INV(RAND(),AVERAGE(Assumptions!$D$17,Assumptions!$F$17),(Assumptions!$F$17-Assumptions!$D$17)/3.29)*8 -> 942927.22 | F10: =_xlfn.NORM.INV(RAND(),AVERAGE(Assumptions!$D$7,Assumptions!$F$7),(Assumptions!$F$7-Assumptions!$D$7)/3.29)*RANDBETWEEN(1,3) -> 1620092.9 | G10: =_xlfn.NORM.INV(RAND(),AVERAGE(Assumptions!$D$8,Assumptions!$F$8),(Assumptions!$F$8-Assumptions!$D$8)/3.29)*44 -> 1464561.2 | H10: =_xlfn.NORM.INV(RAND(),AVERAGE(Assumptions!$D$9,Assumptions!$F$9),(Assumptions!$F$9-Assumptions!$D$9)/3.29)*21 -> 1997479 | I10: =_xlfn.NORM.INV(RAND(),AVERAGE(Assumptions!$D$10,Assumptions!$F$10),(Assumptions!$F$10-Assumptions!$D$10)/3.29)*21 -> 526911.64 | J10: =NORMINV(RAND(),AVERAGE(Assumptions!$D$11,Assumptions!$F$11),(Assumptions!$F$11-Assumptions!$D$11)/3.29)*44 -> 6747226.4 | K10: =_xlfn.NORM.INV(RAND(),AVERAGE(Assumptions!$D$12,Assumptions!$F$12),(Assumptions!$F$12-Assumptions!$D$12)/3.29)*44 -> 8970153.8 | L10: =_xlfn.NORM.INV(RAND(),AVERAGE(Assumptions!$D$13,Assumptions!$F$13),(Assumptions!$F$13-Assumptions!$D$13)/3.29)*44 -> 17524976 | M10: =_xlfn.NORM.INV(RAND(),AVERAGE(Assumptions!$D$14,Assumptions!$F$14),(Assumptions!$F$14-Assumptions!$D$14)/3.29)*44 -> 6119203.1 | N10: =_xlfn.NORM.INV(RAND(),AVERAGE(Assumptions!$D$16,Assumptions!$F$16),(Assumptions!$F$16-Assumptions!$D$16)/3.29)*44 -> 12757413 | O10: =_xlfn.NORM.INV(RAND(),AVERAGE(Assumptions!$D$15,Assumptions!$F$15),(Assumptions!$F$15-Assumptions!$D$15)/3.29)*44 -> 80642284 | P10: =Assumptions!$D$18 -> 14641750 | Q10: =O10-(B10+C10+D10+F10+G10+H10+I10+J10+K10+L10+M10+N10+E10) -> 17078921 | R10: =Q10+P10 -> 31720671
A11: 10 | B11: =_xlfn.NORM.INV(RAND(),AVERAGE(Assumptions!$D$4,Assumptions!$F$4),(Assumptions!$F$4-Assumptions!$D$4)/3.29)*44 -> 1195180 | C11: =_xlfn.NORM.INV(RAND(),AVERAGE(Assumptions!$D$5,Assumptions!$F$5),(Assumptions!$F$5-Assumptions!$D$5)/3.29)*44 -> 1984492.8 | D11: =_xlfn.NORM.INV(RAND(),AVERAGE(Assumptions!$D$6,Assumptions!$F$6),(Assumptions!$F$6-Assumptions!$D$6)/3.29)*RANDBETWEEN(2,5) -> 2240651.2 | E11: =_xlfn.NORM.INV(RAND(),AVERAGE(Assumptions!$D$17,Assumptions!$F$17),(Assumptions!$F$17-Assumptions!$D$17)/3.29)*8 -> 1227364.9 | F11: =_xlfn.NORM.INV(RAND(),AVERAGE(Assumptions!$D$7,Assumptions!$F$7),(Assumptions!$F$7-Assumptions!$D$7)/3.29)*RANDBETWEEN(1,3) -> 2282997.8 | G11: =_xlfn.NORM.INV(RAND(),AVERAGE(Assumptions!$D$8,Assumptions!$F$8),(Assumptions!$F$8-Assumptions!$D$8)/3.29)*44 -> 1080136 | H11: =_xlfn.NORM.INV(RAND(),AVERAGE(Assumptions!$D$9,Assumptions!$F$9),(Assumptions!$F$9-Assumptions!$D$9)/3.29)*21 -> 5033176.6 | I11: =_xlfn.NORM.INV(RAND(),AVERAGE(Assumptions!$D$10,Assumptions!$F$10),(Assumptions!$F$10-Assumptions!$D$10)/3.29)*21 -> 1199916.3 | J11: =NORMINV(RAND(),AVERAGE(Assumptions!$D$11,Assumptions!$F$11),(Assumptions!$F$11-Assumptions!$D$11)/3.29)*44 -> 2971152.6 | K11: =_xlfn.NORM.INV(RAND(),AVERAGE(Assumptions!$D$12,Assumptions!$F$12),(Assumptions!$F$12-Assumptions!$D$12)/3.29)*44 -> 6418088 | L11: =_xlfn.NORM.INV(RAND(),AVERAGE(Assumptions!$D$13,Assumptions!$F$13),(Assumptions!$F$13-Assumptions!$D$13)/3.29)*44 -> 12134012 | M11: =_xlfn.NORM.INV(RAND(),AVERAGE(Assumptions!$D$14,Assumptions!$F$14),(Assumptions!$F$14-Assumptions!$D$14)/3.29)*44 -> 7612902.8 | N11: =_xlfn.NORM.INV(RAND(),AVERAGE(Assumptions!$D$16,Assumptions!$F$16),(Assumptions!$F$16-Assumptions!$D$16)/3.29)*44 -> 9453380.6 | O11: =_xlfn.NORM.INV(RAND(),AVERAGE(Assumptions!$D$15,Assumptions!$F$15),(Assumptions!$F$15-Assumptions!$D$15)/3.29)*44 -> 86457014 | P11: =Assumptions!$D$18 -> 14641750 | Q11: =O11-(B11+C11+D11+F11+G11+H11+I11+J11+K11+L11+M11+N11+E11) -> 31623562 | R11: =Q11+P11 -> 46265313
A12: 11 | B12: =_xlfn.NORM.INV(RAND(),AVERAGE(Assumptions!$D$4,Assumptions!$F$4),(Assumptions!$F$4-Assumptions!$D$4)/3.29)*44 -> 1157443 | C12: =_xlfn.NORM.INV(RAND(),AVERAGE(Assumptions!$D$5,Assumptions!$F$5),(Assumptions!$F$5-Assumptions!$D$5)/3.29)*44 -> 1872203.9 | D12: =_xlfn.NORM.INV(RAND(),AVERAGE(Assumptions!$D$6,Assumptions!$F$6),(Assumptions!$F$6-Assumptions!$D$6)/3.29)*RANDBETWEEN(2,5) -> 6094394.2 | E12: =_xlfn.NORM.INV(RAND(),AVERAGE(Assumptions!$D$17,Assumptions!$F$17),(Assumptions!$F$17-Assumptions!$D$17)/3.29)*8 -> 1051722.3 | F12: =_xlfn.NORM.INV(RAND(),AVERAGE(Assumptions!$D$7,Assumptions!$F$7),(Assumptions!$F$7-Assumptions!$D$7)/3.29)*RANDBETWEEN(1,3) -> 1708072.5 | G12: =_xlfn.NORM.INV(RAND(),AVERAGE(Assumptions!$D$8,Assumptions!$F$8),(Assumptions!$F$8-Assumptions!$D$8)/3.29)*44 -> 1438601.3 | H12: =_xlfn.NORM.INV(RAND(),AVERAGE(Assumptions!$D$9,Assumptions!$F$9),(Assumptions!$F$9-Assumptions!$D$9)/3.29)*21 -> 4253595.9 | I12: =_xlfn.NORM.INV(RAND(),AVERAGE(Assumptions!$D$10,Assumptions!$F$10),(Assumptions!$F$10-Assumptions!$D$10)/3.29)*21 -> 231581.84 | J12: =NORMINV(RAND(),AVERAGE(Assumptions!$D$11,Assumptions!$F$11),(Assumptions!$F$11-Assumptions!$D$11)/3.29)*44 -> 3346713.6 | K12: =_xlfn.NORM.INV(RAND(),AVERAGE(Assumptions!$D$12,Assumptions!$F$12),(Assumptions!$F$12-Assumptions!$D$12)/3.29)*44 -> 7570177.7 | L12: =_xlfn.NORM.INV(RAND(),AVERAGE(Assumptions!$D$13,Assumptions!$F$13),(Assumptions!$F$13-Assumptions!$D$13)/3.29)*44 -> 17058936 | M12: =_xlfn.NORM.INV(RAND(),AVERAGE(Assumptions!$D$14,Assumptions!$F$14),(Assumptions!$F$14-Assumptions!$D$14)/3.29)*44 -> 7505454.3 | N12: =_xlfn.NORM.INV(RAND(),AVERAGE(Assumptions!$D$16,Assumptions!$F$16),(Assumptions!$F$16-Assumptions!$D$16)/3.29)*44 -> 4487617.1 | O12: =_xlfn.NORM.INV(RAND(),AVERAGE(Assumptions!$D$15,Assumptions!$F$15),(Assumptions!$F$15-Assumptions!$D$15)/3.29)*44 -> 1.163515e+08 | P12: =Assumptions!$D$18 -> 14641750 | Q12: =O12-(B12+C12+D12+F12+G12+H12+I12+J12+K12+L12+M12+N12+E12) -> 58574986 | R12: =Q12+P12 -> 73216736
A13: 12 | B13: =_xlfn.NORM.INV(RAND(),AVERAGE(Assumptions!$D$4,Assumptions!$F$4),(Assumptions!$F$4-Assumptions!$D$4)/3.29)*44 -> 1136550.5 | C13: =_xlfn.NORM.INV(RAND(),AVERAGE(Assumptions!$D$5,Assumptions!$F$5),(Assumptions!$F$5-Assumptions!$D$5)/3.29)*44 -> 1902599.3 | D13: =_xlfn.NORM.INV(RAND(),AVERAGE(Assumptions!$D$6,Assumptions!$F$6),(Assumptions!$F$6-Assumptions!$D$6)/3.29)*RANDBETWEEN(2,5) -> 8519266.7 | E13: =_xlfn.NORM.INV(RAND(),AVERAGE(Assumptions!$D$17,Assumptions!$F$17),(Assumptions!$F$17-Assumptions!$D$17)/3.29)*8 -> 895616.48 | F13: =_xlfn.NORM.INV(RAND(),AVERAGE(Assumptions!$D$7,Assumptions!$F$7),(Assumptions!$F$7-Assumptions!$D$7)/3.29)*RANDBETWEEN(1,3) -> 9381710.2 | G13: =_xlfn.NORM.INV(RAND(),AVERAGE(Assumptions!$D$8,Assumptions!$F$8),(Assumptions!$F$8-Assumptions!$D$8)/3.29)*44 -> 1209204.5 | H13: =_xlfn.NORM.INV(RAND(),AVERAGE(Assumptions!$D$9,Assumptions!$F$9),(Assumptions!$F$9-Assumptions!$D$9)/3.29)*21 -> 5508436.9 | I13: =_xlfn.NORM.INV(RAND(),AVERAGE(Assumptions!$D$10,Assumptions!$F$10),(Assumptions!$F$10-Assumptions!$D$10)/3.29)*21 -> 770454.07 | J13: =NORMINV(RAND(),AVERAGE(Assumptions!$D$11,Assumptions!$F$11),(Assumptions!$F$11-Assumptions!$D$11)/3.29)*44 -> 2353241.1 | K13: =_xlfn.NORM.INV(RAND(),AVERAGE(Assumptions!$D$12,Assumptions!$F$12),(Assumptions!$F$12-Assumptions!$D$12)/3.29)*44 -> 6586332.9 | L13: =_xlfn.NORM.INV(RAND(),AVERAGE(Assumptions!$D$13,Assumptions!$F$13),(Assumptions!$F$13-Assumptions!$D$13)/3.29)*44 -> 9534477.9 | M13: =_xlfn.NORM.INV(RAND(),AVERAGE(Assumptions!$D$14,Assumptions!$F$14),(Assumptions!$F$14-Assumptions!$D$14)/3.29)*44 -> 5894186.7 | N13: =_xlfn.NORM.INV(RAND(),AVERAGE(Assumptions!$D$16,Assumptions!$F$16),(Assumptions!$F$16-Assumptions!$D$16)/3.29)*44 -> 8795808 | O13: =_xlfn.NORM.INV(RAND(),AVERAGE(Assumptions!$D$15,Assumptions!$F$15),(Assumptions!$F$15-Assumptions!$D$15)/3.29)*44 -> 1.4273197e+08 | P13: =Assumptions!$D$18 -> 14641750 | Q13: =O13-(B13+C13+D13+F13+G13+H13+I13+J13+K13+L13+M13+N13+E13) -> 80244081 | R13: =Q13+P13 -> 94885831
... A1002: 1001 | B1002: =_xlfn.NORM.INV(RAND(),AVERAGE(Assumptions!$D$4,Assumptions!$F$4),(Assumptions!$F$4-Assumptions!$D$4)/3.29)*44 -> 1214998.6 | C1002: =_xlfn.NORM.INV(RAND(),AVERAGE(Assumptions!$D$5,Assumptions!$F$5),(Assumptions!$F$5-Assumptions!$D$5)/3.29)*44 -> 1606663.2 | D1002: =_xlfn.NORM.INV(RAND(),AVERAGE(Assumptions!$D$6,Assumptions!$F$6),(Assumptions!$F$6-Assumptions!$D$6)/3.29)*RANDBETWEEN(2,5) -> 6751665.4 | E1002: =_xlfn.NORM.INV(RAND(),AVERAGE(Assumptions!$D$17,Assumptions!$F$17),(Assumptions!$F$17-Assumptions!$D$17)/3.29)*8 -> 862571.77 | F1002: =_xlfn.NORM.INV(RAND(),AVERAGE(Assumptions!$D$7,Assumptions!$F$7),(Assumptions!$F$7-Assumptions!$D$7)/3.29)*RANDBETWEEN(1,3) -> 2071192.7 | G1002: =_xlfn.NORM.INV(RAND(),AVERAGE(Assumptions!$D$8,Assumptions!$F$8),(Assumptions!$F$8-Assumptions!$D$8)/3.29)*44 -> 985232.41 | H1002: =_xlfn.NORM.INV(RAND(),AVERAGE(Assumptions!$D$9,Assumptions!$F$9),(Assumptions!$F$9-Assumptions!$D$9)/3.29)*21 -> 5804525.8 | I1002: =_xlfn.NORM.INV(RAND(),AVERAGE(Assumptions!$D$10,Assumptions!$F$10),(Assumptions!$F$10-Assumptions!$D$10)/3.29)*21 -> 1069496.6 | J1002: =NORMINV(RAND(),AVERAGE(Assumptions!$D$11,Assumptions!$F$11),(Assumptions!$F$11-Assumptions!$D$11)/3.29)*44 -> 1725011 | K1002: =_xlfn.NORM.INV(RAND(),AVERAGE(Assumptions!$D$12,Assumptions!$F$12),(Assumptions!$F$12-Assumptions!$D$12)/3.29)*44 -> 8701750.4 | L1002: =_xlfn.NORM.INV(RAND(),AVERAGE(Assumptions!$D$13,Assumptions!$F$13),(Assumptions!$F$13-Assumptions!$D$13)/3.29)*44 -> 12695745 | M1002: =_xlfn.NORM.INV(RAND(),AVERAGE(Assumptions!$D$14,Assumptions!$F$14),(Assumptions!$F$14-Assumptions!$D$14)/3.29)*44 -> 6332631.8 | N1002: =_xlfn.NORM.INV(RAND(),AVERAGE(Assumptions!$D$16,Assumptions!$F$16),(Assumptions!$F$16-Assumptions!$D$16)/3.29)*44 -> 14214607 | O1002: =_xlfn.NORM.INV(RAND(),AVERAGE(Assumptions!$D$15,Assumptions!$F$15),(Assumptions!$F$15-Assumptions!$D$15)/3.29)*44 -> 71326232 | P1002: =Assumptions!$D$18 -> 14641750 | Q1002: =O1002-(B1002+C1002+D1002+F1002+G1002+H1002+I1002+J1002+K1002+L1002+M1002+N1002+E1002) -> 7290139.8 | R1002: =Q1002+P1002 -> 21931890

Sheet Histogram

Sheet Reflection
D3: Personal Reflection | T3: Technical Reflection
D5: This assignment has made me learn more about finances and how important it actually is to save and invest. I also learnt that kids are very expensive and I rather just own pets in future. This assignment was actually a bit fun, especially seeing the numbers of how much I may be earning in the future. Additionally, I took note of how small expenses do add up and visualizing it was very eye opening. I also reflected on my own financial habits and I am trying to be more money concious, why do I spend so much on one cup of coffee? I don't view this simulation as a tool to help me see future expenses and outcomes, I see it more as a mirror as to how my life could be. Although this simulation does not include a yacht, it does include the information to tell me how many cups of coffee I'd need to skip to afford one. I think the most important thing I learnt is how financial planning is not only about numbers, it's about being able to align my goals and values with money. Finance goes hand in hand with mindfulness, and humor to soften the blow of reality. | T5: This assignment really helped me develop my skills in excel. From watching videos on excel shortcuts to playing around and figuring things out, my excel skills have being taken to a new level. I think this assignment also helped me with my problem solving skills, by breaking down some complex financial questions I had. I have being paying more attention to detail and trying to order and manage data more effectively. I feel more confident with my skills in excel and now feel like I can actually say that I know how to make use of excel.
